lewd_dl/LewdDL.py
lewd_dl/__init__.py
lewd_dl/__main__.py
lewd_dl/__vars__.py
lewd_dl/log.py
lewd_dl/options.py
lewd_dl/video.py
lewd_dl-0.1.0.dist-info/LICENSE
lewd_dl-0.1.0.dist-info/METADATA
lewd_dl-0.1.0.dist-info/WHEEL
lewd_dl-0.1.0.dist-info/entry_points.txt
lewd_dl-0.1.0.dist-info/top_level.txt
lewd_dl-0.1.0.dist-info/RECORD
