Metadata-Version: 2.1
Name: lewd-dl
Version: 0.1.0
Summary: Download videos from lewd websites
Home-page: https://github.com/b3yc0d3/lewd-dl
Author: b3yc0d3
Author-email: b3yc0d3@gmail.com
License: UNKNOWN
Project-URL: Issue tracker, https://github.com/b3yc0d3/lewd-dl/issues
Platform: UNKNOWN
Classifier: Environment :: Console
Classifier: Natural Language :: English
Classifier: Development Status :: 3 - Alpha
Classifier: Intended Audience :: Other Audience
Classifier: Programming Language :: Python :: 3.10
Classifier: License :: OSI Approved :: Mozilla Public License 2.0 (MPL 2.0)
Classifier: Operating System :: POSIX :: Linux
Classifier: Topic :: Internet
License-File: LICENSE
Requires-Dist: m3u8 (==3.5.0)
Requires-Dist: rich (==13.3.5)
Requires-Dist: requests (==2.30.0)
Requires-Dist: validators (==0.20.0)
Requires-Dist: beautifulsoup4 (==4.12.2)
